FlexiLogger/__init__.py
FlexiLogger/gettraceback.py
FlexiLogger/logger.py
FlexiLogger-1.0.0.dist-info/LICENSE
FlexiLogger-1.0.0.dist-info/METADATA
FlexiLogger-1.0.0.dist-info/WHEEL
FlexiLogger-1.0.0.dist-info/top_level.txt
FlexiLogger-1.0.0.dist-info/RECORD
