Metadata-Version: 2.2
Name: FlexiLogger
Version: 1.0.0
Summary: A customizable logger and traceback handler for Python applications
Home-page: https://github.com/Neizvestnyj/FlexiLogger
Author: Neizvestnyj
Author-email: pikromat1995@gmail.com
Classifier: Programming Language :: Python :: 3
Classifier: License :: OSI Approved :: MIT License
Classifier: Operating System :: OS Independent
Requires-Python: >=3.7
License-File: LICENSE
Dynamic: author
Dynamic: author-email
Dynamic: classifier
Dynamic: description
Dynamic: description-content-type
Dynamic: home-page
Dynamic: requires-python
Dynamic: summary
